chi/__init__.py
chi/_covariate_models.py
chi/_error_models.py
chi/_inference.py
chi/_log_pdfs.py
chi/_mechanistic_models.py
chi/_population_filters.py
chi/_population_models.py
chi/_predictive_models.py
chi/_problems.py
chi/library/__init__.py
chi/library/_data_library_api.py
chi/library/_model_library_api.py
chi/library/data_library/lxf_control_growth.csv
chi/library/data_library/lxf_high_erlotinib_dose.csv
chi/library/data_library/lxf_low_erlotinib_dose.csv
chi/library/data_library/lxf_medium_erlotinib_dose.csv
chi/library/data_library/lxf_single_erlotinib_dose.csv
chi/library/model_library/pk_one_comp.xml
chi/library/model_library/temporary_full_pkpd_model.xml
chi/library/model_library/tgi_Koch_2009.xml
chi/library/model_library/tgi_Koch_2009_reparametrised.xml
chi/plots/__init__.py
chi/plots/_base.py
chi/plots/_optimisation.py
chi/plots/_residuals.py
chi/plots/_sampling.py
chi/plots/_time_series.py
chi/tests/test_covariate_models.py
chi/tests/test_data_library_api.py
chi/tests/test_error_models.py
chi/tests/test_inference.py
chi/tests/test_log_pdfs.py
chi/tests/test_mechanistic_models.py
chi/tests/test_model_library_api.py
chi/tests/test_plots_optimisation.py
chi/tests/test_plots_residuals.py
chi/tests/test_plots_sampling.py
chi/tests/test_plots_time_series.py
chi/tests/test_population_filters.py
chi/tests/test_population_models.py
chi/tests/test_predictive_models.py
chi/tests/test_problems.py
chi_drm-1.0.3.dist-info/licenses/LICENSE.md
chi_drm-1.0.3.dist-info/METADATA
chi_drm-1.0.3.dist-info/WHEEL
chi_drm-1.0.3.dist-info/top_level.txt
chi_drm-1.0.3.dist-info/RECORD
