Metadata-Version: 2.4
Name: chi-drm
Version: 1.0.3
Summary: A python package to model dose response dynamics.
Author-email: David Augustin <david.augustin@cervify.com>
License: BSD 3-Clause License
Project-URL: Documentation, https://chi.readthedocs.io
Project-URL: Repository, https://github.com/DavAug/chi
Keywords: python,pkpd,mipd,pharmacokinetics,pharmacodynamics,dose-response,modelling,simulation
Classifier: Programming Language :: Python :: 3
Classifier: Operating System :: OS Independent
Requires-Python: >=3.11
License-File: LICENSE.md
Requires-Dist: arviz>=0.17
Requires-Dist: myokit>=1.34
Requires-Dist: numpy>=1.17
Requires-Dist: pandas>=0.24
Requires-Dist: pints>=0.4
Requires-Dist: plotly>=4.8.1
Requires-Dist: scipy>=1.11
Requires-Dist: tqdm>=4.46.1
Requires-Dist: xarray>=0.19
Provides-Extra: docs
Requires-Dist: sphinx-rtd-theme>=1.3; extra == "docs"
Requires-Dist: sphinx!=1.7.3,>=1.5; extra == "docs"
Requires-Dist: sphinx-copybutton>=0.5.2; extra == "docs"
Provides-Extra: notebooks
Requires-Dist: jupyter==1.0.0; extra == "notebooks"
Dynamic: license-file
